DomApi/__init__.py
DomApi/config.py
DomApi/monitor.py
DomApi/rest_wrapper.py
DomApi/worker.py
DomApi/resources/request_schema.json
DomApi/resources/response_schema.json
DomApi/tests/__init__.py
DomApi/tests/test_worker.py
DomApi-1.7.0.dist-info/LICENSE
DomApi-1.7.0.dist-info/METADATA
DomApi-1.7.0.dist-info/WHEEL
DomApi-1.7.0.dist-info/top_level.txt
DomApi-1.7.0.dist-info/RECORD
