Metadata-Version: 2.1
Name: DomApi
Version: 1.7.0
Summary: Python tool for completion time analysis of batch pizza orders
Home-page: https://github.com/jtruxon/DomApi
Author: James Truxon
Author-email: contact@jamestruxon.com
License: UNKNOWN
Platform: UNKNOWN
Classifier: Development Status :: 2 - Pre-Alpha
Classifier: Environment :: Web Environment
Classifier: Intended Audience :: Developers
Classifier: License :: OSI Approved :: MIT License
Classifier: Operating System :: POSIX :: Linux
Classifier: Programming Language :: Python :: 3.9
License-File: LICENSE
Requires-Dist: werkzeug (==0.16.1)
Requires-Dist: flask (==1.1.4)
Requires-Dist: flask-restplus
Requires-Dist: jsonschema
Requires-Dist: gunicorn
Requires-Dist: pytest
